mlfoundry/__init__.py
mlfoundry/__main__.py
mlfoundry/artifact/__init__.py
mlfoundry/artifact/truefoundry_artifact_repo.py
mlfoundry/background/__init__.py
mlfoundry/background/events.py
mlfoundry/background/interface.py
mlfoundry/background/sender.py
mlfoundry/background/system_metrics.py
mlfoundry/background/utils.py
mlfoundry/cli/__init__.py
mlfoundry/cli/cli_interface.py
mlfoundry/cli/commands/__init__.py
mlfoundry/cli/commands/download.py
mlfoundry/cli/commands/login.py
mlfoundry/constants.py
mlfoundry/enums.py
mlfoundry/env_vars.py
mlfoundry/exceptions.py
mlfoundry/git_info.py
mlfoundry/integrations/__init__.py
mlfoundry/integrations/transformers.py
mlfoundry/internal_namespace.py
mlfoundry/log_types/__init__.py
mlfoundry/log_types/artifacts/artifact.py
mlfoundry/log_types/artifacts/constants.py
mlfoundry/log_types/artifacts/dataset.py
mlfoundry/log_types/artifacts/general_artifact.py
mlfoundry/log_types/artifacts/model.py
mlfoundry/log_types/artifacts/utils.py
mlfoundry/log_types/image/__init__.py
mlfoundry/log_types/image/constants.py
mlfoundry/log_types/image/image.py
mlfoundry/log_types/image/image_normalizer.py
mlfoundry/log_types/image/types.py
mlfoundry/log_types/model_artifact.py
mlfoundry/log_types/plot.py
mlfoundry/log_types/pydantic_base.py
mlfoundry/log_types/utils.py
mlfoundry/logger.py
mlfoundry/login.py
mlfoundry/metrics/__init__.py
mlfoundry/metrics/v1/__init__.py
mlfoundry/metrics/v1/base_metrics.py
mlfoundry/metrics/v1/binary_classification_metrics.py
mlfoundry/metrics/v1/multiclass_classification_metrics.py
mlfoundry/metrics/v1/regression_metrics.py
mlfoundry/metrics/v1/timeseries_metrics.py
mlfoundry/metrics/v2/__init__.py
mlfoundry/metrics/v2/base_metrics.py
mlfoundry/metrics/v2/custom_metric_types.py
mlfoundry/metrics/v2/multiclass_classification_metrics.py
mlfoundry/metrics/v2/regression_metrics.py
mlfoundry/metrics/v2/timeseries_metrics.py
mlfoundry/metrics/v2/utils.py
mlfoundry/mlfoundry_api.py
mlfoundry/mlfoundry_run.py
mlfoundry-0.11.5.dist-info/METADATA
mlfoundry-0.11.5.dist-info/WHEEL
mlfoundry-0.11.5.dist-info/entry_points.txt
mlfoundry-0.11.5.dist-info/RECORD
