Metadata-Version: 2.1
Name: mlfoundry
Version: 0.11.5
Summary: Truefoundry's Experiment Tracking, Model Registry and Model Monitoring Library
Home-page: https://truefoundry.com
Author: Abhishek Choudhary
Author-email: abhichoudhary06@gmail.com
Requires-Python: >=3.8,<4
Classifier: Programming Language :: Python :: 3
Classifier: Programming Language :: Python :: 3.8
Classifier: Programming Language :: Python :: 3.9
Classifier: Programming Language :: Python :: 3.10
Classifier: Programming Language :: Python :: 3.11
Classifier: Programming Language :: Python :: 3.12
Requires-Dist: GitPython (>=3.1.41,<4.0.0)
Requires-Dist: PyJWT (>=2.4.0,<3.0.0)
Requires-Dist: click (>=8.0.0,<9.0.0)
Requires-Dist: coolname (>=1.1.0,<2.0.0)
Requires-Dist: filelock (>=3.8.0,<4.0.0)
Requires-Dist: importlib-metadata (>=4.11.3,<8.0.0)
Requires-Dist: numpy (>=1.23.0,<2.0.0) ; python_version < "3.12"
Requires-Dist: numpy (>=1.26.0,<2.0.0) ; python_version >= "3.12"
Requires-Dist: pandas (>=1.0.0,<3.0.0) ; python_version < "3.10"
Requires-Dist: pandas (>=1.4.0,<3.0.0) ; python_version >= "3.10"
Requires-Dist: psutil (>=5.9.0,<7.0.0)
Requires-Dist: pydantic (>=1.8.2,<3.0.0)
Requires-Dist: rich (>=13.7,<14.0)
Requires-Dist: scikit-learn (>=0.24.2,<2.0.0) ; python_version < "3.10"
Requires-Dist: scikit-learn (>=1.0.2,<3.0.0) ; python_version >= "3.10"
Requires-Dist: tfy-mlflow-client (==0.0.56)
Requires-Dist: tqdm (>=4.62.3,<5.0.0)
Requires-Dist: urllib3 (>=1.26.18,<3)
Project-URL: Repository, https://github.com/truefoundry/mlfoundry
